MANIFEST.in
README.rst
setup.py
gdelt_util/__init__.py
gdelt_util.egg-info/PKG-INFO
gdelt_util.egg-info/SOURCES.txt
gdelt_util.egg-info/dependency_links.txt
gdelt_util.egg-info/not-zip-safe
gdelt_util.egg-info/requires.txt
gdelt_util.egg-info/top_level.txt