Metadata-Version: 1.0
Name: gdelt-util
Version: 0.14
Summary: Utilites exploring GDELT data set
Home-page: http://github.com/davefol/gdelt_util
Author: Dave Fol
Author-email: dof5@cornell.edu
License: GNU
Platform: UNKNOWN
